MANIFEST.in
README.md
setup.py
araucaria/__init__.py
araucaria/utils.py
araucaria/version
araucaria.egg-info/PKG-INFO
araucaria.egg-info/SOURCES.txt
araucaria.egg-info/dependency_links.txt
araucaria.egg-info/requires.txt
araucaria.egg-info/top_level.txt
araucaria/fit/__init__.py
araucaria/fit/lcfit.py
araucaria/io/__init__.py
araucaria/io/io_hdf5.py
araucaria/io/io_read.py
araucaria/io/io_write.py
araucaria/linalg/__init__.py
araucaria/linalg/la.py
araucaria/main/__init__.py
araucaria/main/collection.py
araucaria/main/dataset.py
araucaria/main/group.py
araucaria/main/report.py
araucaria/plot/__init__.py
araucaria/plot/fig_lcf.py
araucaria/plot/fig_lsf.py
araucaria/plot/fig_stats.py
araucaria/plot/fig_xas.py
araucaria/plot/template.py
araucaria/stats/__init__.py
araucaria/stats/cluster.py
araucaria/stats/genesd.py
araucaria/stats/pca.py
araucaria/stats/signal.py
araucaria/testdata/20K_GOE_Fe_K_240.00000.xdi
araucaria/testdata/20K_GOE_Fe_K_240.00001.xdi
araucaria/testdata/20K_GOE_Fe_K_240.00002.xdi
araucaria/testdata/20K_GOE_Fe_K_240.00003.xdi
araucaria/testdata/20K_GOE_Fe_K_240.00004.xdi
araucaria/testdata/Fe_database.h5
araucaria/testdata/__init__.py
araucaria/testdata/dnd_glitchfile.dat
araucaria/testdata/dnd_testfile1.dat
araucaria/testdata/dnd_testfile2.dat
araucaria/testdata/dnd_testfile3.dat
araucaria/testdata/p65_testfile.xdi
araucaria/testdata/rosner.dat
araucaria/testdata/test_lcf_report.log
araucaria/testdata/utils.py
araucaria/testdata/xmu_testfile.xmu
araucaria/xas/__init__.py
araucaria/xas/autobk.py
araucaria/xas/deglitch.py
araucaria/xas/merge.py
araucaria/xas/normalize.py
araucaria/xas/xasft.py
araucaria/xas/xasutils.py
araucaria/xrdb/__init__.py
araucaria/xrdb/chem.py
araucaria/xrdb/xray.py
araucaria/xrdb/data/ElamDB12.txt
araucaria/xrdb/data/elam.db