Metadata-Version: 1.0
Name: araucaria
Version: 0.1.11
Summary: Python library to manipulate XAFS spectra
Home-page: https://github.com/marcoalsina/araucaria
Author: Marco A. Alsina
Author-email: marco.alsina@utalca.cl
License: BSD
Platform: UNKNOWN
